biovalid/__init__.py
biovalid/__main__.py
biovalid/arg_parser.py
biovalid/biovalidator.py
biovalid/enum.py
biovalid/logger.py
biovalid/version.py
biovalid/util/__init__.py
biovalid/util/gff/__init__.py
biovalid/util/gff/legacy_so_mapping.py
biovalid/util/gff/obo_parser.py
biovalid/util/gff/pre_parsed_valid_types.txt
biovalid/util/gff/so_ontologies.obo
biovalid/util/vcf/vcf_models.py
biovalid/validators/__init__.py
biovalid/validators/bai.py
biovalid/validators/bam.py
biovalid/validators/base.py
biovalid/validators/fasta.py
biovalid/validators/fastq.py
biovalid/validators/genbank.py
biovalid/validators/gff.py
biovalid/validators/vcf.py
biovalid-0.4.0.dist-info/METADATA
biovalid-0.4.0.dist-info/WHEEL
biovalid-0.4.0.dist-info/entry_points.txt
biovalid-0.4.0.dist-info/RECORD
