Metadata-Version: 2.4
Name: biovalid
Version: 0.4.0
Summary: Quick validation of bioinformatics files
Project-URL: Homepage, https://github.com/RIVM-bioinformatics/biovalid/
Project-URL: Documentation, https://rivm-bioinformatics.github.io/biovalid/
Author-email: Gino Raaijmakers <gino.raaijmakers@rivm.nl>, RIVM Bioinformatics <ids-bioinformatics@rivm.nl>
License-Expression: AGPL-3.0
Keywords: Bioinformatics
Classifier: Development Status :: 4 - Beta
Classifier: Intended Audience :: Developers
Classifier: Intended Audience :: Science/Research
Classifier: Operating System :: OS Independent
Classifier: Programming Language :: Python :: 3.10
Classifier: Topic :: Scientific/Engineering :: Bio-Informatics
Requires-Python: >=3.10
